mozi_ai_x/__init__.py
mozi_ai_x/py.typed
mozi_ai_x/database/__init__.py
mozi_ai_x/database/database.py
mozi_ai_x/pyarmor_runtime_009666/__init__.py
mozi_ai_x/pyarmor_runtime_009666/pyarmor_runtime.pyd
mozi_ai_x/simulation/__init__.py
mozi_ai_x/simulation/args.py
mozi_ai_x/simulation/contact.py
mozi_ai_x/simulation/doctrine.py
mozi_ai_x/simulation/logged_message.py
mozi_ai_x/simulation/mount.py
mozi_ai_x/simulation/reference_point.py
mozi_ai_x/simulation/response.py
mozi_ai_x/simulation/scenario.py
mozi_ai_x/simulation/sensor.py
mozi_ai_x/simulation/side.py
mozi_ai_x/simulation/sideway.py
mozi_ai_x/simulation/sim_event.py
mozi_ai_x/simulation/situ_interpret.py
mozi_ai_x/simulation/situation.py
mozi_ai_x/simulation/types.py
mozi_ai_x/simulation/waypoint.py
mozi_ai_x/simulation/weapon_impact.py
mozi_ai_x/simulation/weather.py
mozi_ai_x/simulation/action/__init__.py
mozi_ai_x/simulation/action/base.py
mozi_ai_x/simulation/action/change_mission_status.py
mozi_ai_x/simulation/action/end_scenario.py
mozi_ai_x/simulation/action/lua_script.py
mozi_ai_x/simulation/action/message.py
mozi_ai_x/simulation/action/points.py
mozi_ai_x/simulation/action/teleport_in_area.py
mozi_ai_x/simulation/active_unit/__init__.py
mozi_ai_x/simulation/active_unit/aircraft.py
mozi_ai_x/simulation/active_unit/base.py
mozi_ai_x/simulation/active_unit/facility.py
mozi_ai_x/simulation/active_unit/group.py
mozi_ai_x/simulation/active_unit/satellite.py
mozi_ai_x/simulation/active_unit/ship.py
mozi_ai_x/simulation/active_unit/submarine.py
mozi_ai_x/simulation/active_unit/unguided_weapon.py
mozi_ai_x/simulation/active_unit/weapon.py
mozi_ai_x/simulation/base/__init__.py
mozi_ai_x/simulation/base/base.py
mozi_ai_x/simulation/condition/__init__.py
mozi_ai_x/simulation/condition/base.py
mozi_ai_x/simulation/condition/lua_script.py
mozi_ai_x/simulation/condition/scen_has_started.py
mozi_ai_x/simulation/condition/side_posture.py
mozi_ai_x/simulation/loadout/__init__.py
mozi_ai_x/simulation/loadout/base.py
mozi_ai_x-0.3.7.dist-info/METADATA
mozi_ai_x-0.3.7.dist-info/WHEEL
mozi_ai_x-0.3.7.dist-info/top_level.txt
mozi_ai_x-0.3.7.dist-info/RECORD
