Metadata-Version: 2.4
Name: mozi_ai_x
Version: 0.3.7
Summary: Mozi AI async version (pyarmor build)
License: MIT
Requires-Python: >=3.10
Requires-Dist: betterproto>=2.0.0b6
Requires-Dist: psutil>=6.1.1
Requires-Dist: grpcio>=1.70.0
Requires-Dist: numpy>=2.2.2
